cachethq_client/__init__.py
cachethq_client/api/__init__.py
cachethq_client/api/component_groups_api.py
cachethq_client/api/components_api.py
cachethq_client/api/default_api.py
cachethq_client/api/general_api.py
cachethq_client/api/incidents_api.py
cachethq_client/api/metrics_api.py
cachethq_client/api_client.py
cachethq_client/configuration.py
cachethq_client/models/__init__.py
cachethq_client/models/component.py
cachethq_client/models/component_group.py
cachethq_client/models/component_group_response.py
cachethq_client/models/component_response.py
cachethq_client/models/error.py
cachethq_client/models/incident.py
cachethq_client/models/incident_response.py
cachethq_client/models/incident_update_response.py
cachethq_client/models/list_component_groups_response.py
cachethq_client/models/list_components_response.py
cachethq_client/models/list_incident_updates_response.py
cachethq_client/models/list_incidents_response.py
cachethq_client/models/list_metric_points_response.py
cachethq_client/models/list_metrics_response.py
cachethq_client/models/meta_data.py
cachethq_client/models/metric.py
cachethq_client/models/metric_point.py
cachethq_client/models/metric_points_response.py
cachethq_client/models/metrics_response.py
cachethq_client/models/pagination.py
cachethq_client/models/ping.py
cachethq_client/models/single_component_group_response.py
cachethq_client/models/single_component_response.py
cachethq_client/models/single_incident_response.py
cachethq_client/models/single_incident_update_response.py
cachethq_client/models/single_metric_point_response.py
cachethq_client/models/single_metric_response.py
cachethq_client/models/tag.py
cachethq_client/models/version.py
cachethq_client/rest.py
cachethq_client-1.0.4.dist-info/METADATA
cachethq_client-1.0.4.dist-info/WHEEL
cachethq_client-1.0.4.dist-info/RECORD
